hydra_plugins/hydra_rq_launcher/__init__.py
hydra_plugins/hydra_rq_launcher/_core.py
hydra_plugins/hydra_rq_launcher/config.py
hydra_plugins/hydra_rq_launcher/rq_launcher.py
hydra_rq_launcher-1.2.0.dist-info/METADATA
hydra_rq_launcher-1.2.0.dist-info/WHEEL
hydra_rq_launcher-1.2.0.dist-info/top_level.txt
hydra_rq_launcher-1.2.0.dist-info/RECORD
