Metadata-Version: 2.1
Name: hydra-rq-launcher
Version: 1.2.0
Summary: Redis Queue (RQ) Launcher for Hydra apps
Home-page: https://github.com/facebookresearch/hydra/
Author: Jan-Matthis Lueckmann, Omry Yadan
Author-email: mail@jan-matthis.de, omry@fb.com
License: UNKNOWN
Platform: UNKNOWN
Classifier: License :: OSI Approved :: MIT License
Classifier: Programming Language :: Python :: 3.6
Classifier: Programming Language :: Python :: 3.7
Classifier: Programming Language :: Python :: 3.8
Classifier: Programming Language :: Python :: 3.9
Classifier: Programming Language :: Python :: 3.10
Classifier: Operating System :: MacOS
Classifier: Operating System :: POSIX :: Linux
Requires-Dist: cloudpickle
Requires-Dist: fakeredis (<1.7.4)
Requires-Dist: hydra-core (>=1.1.0.dev7)
Requires-Dist: rq (>=1.5.1)
